LICENSE
README.md
setup.py
pyFlarum.egg-info/PKG-INFO
pyFlarum.egg-info/SOURCES.txt
pyFlarum.egg-info/dependency_links.txt
pyFlarum.egg-info/requires.txt
pyFlarum.egg-info/top_level.txt
pyflarum/__init__.py
pyflarum/datetime_conversions.py
pyflarum/error_handler.py
pyflarum/extensions.py
pyflarum/client/__init__.py
pyflarum/client/custom_types.py
pyflarum/client/session.py
pyflarum/client/extensions/__init__.py
pyflarum/client/extensions/absolutely_all.py
pyflarum/client/extensions/admin.py
pyflarum/client/extensions/advanced_search.py
pyflarum/client/extensions/commands.py
pyflarum/client/extensions/watch.py
pyflarum/client/extensions/flarum/Askvortsov_ModeratorWarnings.py
pyflarum/client/extensions/flarum/Askvortsov_ReplyTemplates.py
pyflarum/client/extensions/flarum/Blomstra_Realtime.py
pyflarum/client/extensions/flarum/Flarum_Approval.py
pyflarum/client/extensions/flarum/Flarum_Flags.py
pyflarum/client/extensions/flarum/Flarum_Likes.py
pyflarum/client/extensions/flarum/Flarum_Lock.py
pyflarum/client/extensions/flarum/Flarum_Markdown.py
pyflarum/client/extensions/flarum/Flarum_Sticky.py
pyflarum/client/extensions/flarum/Flarum_Subscriptions.py
pyflarum/client/extensions/flarum/Flarum_Suspend.py
pyflarum/client/extensions/flarum/Flarum_Tags.py
pyflarum/client/extensions/flarum/FoF_BestAnswer.py
pyflarum/client/extensions/flarum/FoF_Byobu.py
pyflarum/client/extensions/flarum/FoF_Merge.py
pyflarum/client/extensions/flarum/FoF_PreventNecrobumping.py
pyflarum/client/extensions/flarum/FoF_Spamblock.py
pyflarum/client/extensions/flarum/FoF_Split.py
pyflarum/client/extensions/flarum/FoF_UserBio.py
pyflarum/client/extensions/flarum/FoF_UsernameRequest.py
pyflarum/client/extensions/flarum/Malago_Achievements.py
pyflarum/client/extensions/flarum/__init__.py
pyflarum/client/flarum/__init__.py
pyflarum/client/flarum/core/__init__.py
pyflarum/client/flarum/core/discussions.py
pyflarum/client/flarum/core/filters.py
pyflarum/client/flarum/core/forum.py
pyflarum/client/flarum/core/groups.py
pyflarum/client/flarum/core/notifications.py
pyflarum/client/flarum/core/posts.py
pyflarum/client/flarum/core/users.py