Metadata-Version: 2.1
Name: pyFlarum
Version: 1.0.2
Summary: An unofficial Python package for manipulating with Flarum's API
Home-page: https://github.com/CWKevo/pyflarum
Author: SKevo
Author-email: me@kevo.link
License: MIT
Keywords: Flarum,forum software,api,Flarum api,bot,userbot,server,client
Classifier: Development Status :: 4 - Beta
Classifier: Intended Audience :: Developers
Classifier: Topic :: Software Development :: Build Tools
Classifier: License :: OSI Approved :: MIT License
Classifier: Programming Language :: Python :: 3.6
Classifier: Programming Language :: Python :: 3.7
Classifier: Programming Language :: Python :: 3.8
Classifier: Programming Language :: Python :: 3.9
Classifier: Programming Language :: Python :: 3.10
Classifier: Programming Language :: Python :: 3.11
License-File: LICENSE
